db_connectors/__init__.py
db_connectors/base.py
db_connectors/kafka_connector.py
db_connectors/kafka_producer_connector.py
db_connectors/minio_connector.py
db_connectors/timescale_connector.py
db_connectors-1.2.2.dist-info/METADATA
db_connectors-1.2.2.dist-info/WHEEL
db_connectors-1.2.2.dist-info/RECORD
