Metadata-Version: 2.4
Name: db-connectors
Version: 1.2.2
Summary: A collection of database and message broker connectors for Python applications
Project-URL: Homepage, https://github.com/deepblue597/db-connectors
Project-URL: Repository, https://github.com/deepblue597/db-connectors.git
Project-URL: Issues, https://github.com/deepblue597/db-connectors/issues
Author-email: Jason <ikakandris@gmail.com>
License: MIT
Keywords: connectors,database,kafka,minio,postgresql,timescale
Classifier: Development Status :: 3 - Alpha
Classifier: Intended Audience :: Developers
Classifier: License :: OSI Approved :: MIT License
Classifier: Programming Language :: Python :: 3
Classifier: Programming Language :: Python :: 3.12
Classifier: Topic :: Database
Classifier: Topic :: Software Development :: Libraries :: Python Modules
Requires-Python: >=3.12
Requires-Dist: boto3>=1.34.0
Requires-Dist: confluent-kafka>=2.3.0
Requires-Dist: psycopg2-binary>=2.9.0
Requires-Dist: quixstreams>=3.23.0
Requires-Dist: ruff>=0.14.3
Requires-Dist: sqlalchemy>=2.0.0
